{"browser_network.md":"FnQANw-z","css_animate.md":"BWLahp3S","css_background.md":"Bo_dvv5y","css_box.md":"C9ehp3Ke","css_color.md":"CQf0U76A","css_cursor.md":"Bm6sZoXS","css_index.md":"BlMp28O7","css_layout.md":"BflFdHu0","css_text.md":"DuLQjfTy","css_unit.md":"Dh6a61HZ","db_mongo.md":"CvyFEzWZ","db_mongoose.md":"BXXo_4pI","db_mongosh.md":"D7nNRBT4","docker_docker-compose.md":"BprbFK_6","docker_docker-desktop.md":"COj6nmDm","docker_docker-file.md":"4alPU0H7","docker_images.md":"Co6wvjP-","docker_index.md":"Cbf8v31-","express_index.md":"CveJyMf8","extension_extension.md":"Hgt5hMGP","extension_index.md":"mvhNmF9h","extension_plasmo.md":"B3ne6Wsk","git_gitignore.md":"BBgRAWyz","git_index.md":"Ck10hvhx","home.md":"WNgzfGH-","hot-knowledge_fa.md":"DlBsnjiH","hot-knowledge_index.md":"DD6U-h27","index.md":"BX-K8pNh","javascript_array.md":"CbBs4Fqc","javascript_bom.md":"COPVnnfN","javascript_collections.md":"g0TNNBLC","javascript_dom.md":"PUXvAHEu","javascript_function.md":"C-mnJA_O","javascript_object.md":"Dg6IAQJo","javascript_promise.md":"C3vd_M-j","javascript_regexp.md":"L_PJj5sF","javascript_string.md":"MBTOoAYv","linux_file.md":"D3eiDAi6","linux_index.md":"CZoT6NIQ","linux_shell.md":"dS2ZWJph","linux_ssh.md":"DVXQsmQt","linux_ubuntu.md":"07l_0oiH","linux_user.md":"BsLS0v2K","linux_wsl.md":"BaRX7HxY","miscellaneous_index.md":"mlkr9NMI","miscellaneous_new_year.md":"CZndXx_I","nestjs_index.md":"dFAyZb4s","nginx_index.md":"DNIec5mT","nginx_ssl.md":"YWf68x2S","nginx_upstream.md":"DvXkFPlR","nginx_variate.md":"Cey0yCfF","node_file.md":"CNuJsxzM","node_index.md":"CY80Hrvb","react_index.md":"CEicqgNF","react_list.md":"d2UoS4Ky","rxjs_rxjs.md":"CkruJq2t","snippet_index.md":"DJuWjAeW","snippet_mongoose.md":"CLmab3tc","snippet_nestjs.md":"DzRojehx","snippet_vue.md":"iy0LfIOT","typescript_descriptor.md":"Di6cefDw","typescript_index.md":"BEm-3jpe","typescript_type-challenges.md":"D-Idobtv","typescript_type.md":"C-qyrviu","uni-app_index.md":"DIFo8CQC","vim_index.md":"DU1YG3TV","vue_index.md":"DmF5pAS3","vue_pinia.md":"DdyPE9G3","vue_router.md":"Baf091JU"}
